pyhydra/__init__.py
pyhydra/adml_classification.py
pyhydra/base.py
pyhydra/classification.py
pyhydra/cli.py
pyhydra/clustering.py
pyhydra/hydra_clustering.py
pyhydra/main.py
pyhydra/utils.py
pyHYDRA-1.0.8.dist-info/LICENSE
pyHYDRA-1.0.8.dist-info/METADATA
pyHYDRA-1.0.8.dist-info/WHEEL
pyHYDRA-1.0.8.dist-info/entry_points.txt
pyHYDRA-1.0.8.dist-info/top_level.txt
pyHYDRA-1.0.8.dist-info/RECORD
