Metadata-Version: 2.1
Name: pyHYDRA
Version: 1.0.8
Summary: A fast python implementation of HYDRA for classification and clustering
Home-page: https://github.com/anbai106/pyhydra
Author: junhao.wen
Author-email: junhao.wen89@email.com
License: UNKNOWN
Platform: UNKNOWN
Classifier: Programming Language :: Python :: 3
Classifier: License :: OSI Approved :: MIT License
Classifier: Operating System :: OS Independent
